memento_cli/__init__.py
memento_cli/browser.py
memento_cli/memento.py
memento_cli-0.0.4.dist-info/METADATA
memento_cli-0.0.4.dist-info/WHEEL
memento_cli-0.0.4.dist-info/entry_points.txt
memento_cli-0.0.4.dist-info/RECORD
