Metadata-Version: 2.1
Name: memento-cli
Version: 0.0.4
Summary: Examine snapshots in eeb archives such as the Internet Archive's Wayback Machine
License: MIT
Author: Ed Summers
Author-email: ehs@pobox.com
Requires-Python: >=3.9,<4.0
Classifier: License :: OSI Approved :: MIT License
Classifier: Programming Language :: Python :: 3
Classifier: Programming Language :: Python :: 3.9
Classifier: Programming Language :: Python :: 3.10
Classifier: Programming Language :: Python :: 3.11
Classifier: Programming Language :: Python :: 3.12
Requires-Dist: click (>=8.1.7,<9.0.0)
Requires-Dist: requests (>=2.31.0,<3.0.0)
Requires-Dist: selenium (>=4.12.0,<5.0.0)
